torchaudio_filters/__init__.py
torchaudio_filters/filters.py
torchaudio_filters/pad.py
torchaudio_filters-0.2.1.dist-info/LICENSE
torchaudio_filters-0.2.1.dist-info/METADATA
torchaudio_filters-0.2.1.dist-info/WHEEL
torchaudio_filters-0.2.1.dist-info/RECORD
