Metadata-Version: 2.1
Name: torchaudio-filters
Version: 0.2.1
Summary: High-pass and low-pass filters implemented as modules with torchaudio
License: GPLv3
Author: BlakeJC94
Author-email: blakejamescook@gmail.com
Requires-Python: >=3.10,<4.0
Classifier: License :: Other/Proprietary License
Classifier: Programming Language :: Python :: 3
Classifier: Programming Language :: Python :: 3.10
Classifier: Programming Language :: Python :: 3.11
Classifier: Programming Language :: Python :: 3.12
Requires-Dist: scipy (>=1.12.0,<2.0.0)
Requires-Dist: torchaudio (>=2.0.0,<3.0.0)
